mb_test/__init__.py
mb_test/_version.py
mb_test_task/__init__.py
mb_test_task/_version.py
mb_test_task/base.py
mb_test_task-0.0.0.dist-info/LICENSE
mb_test_task-0.0.0.dist-info/METADATA
mb_test_task-0.0.0.dist-info/WHEEL
mb_test_task-0.0.0.dist-info/top_level.txt
mb_test_task-0.0.0.dist-info/RECORD
